robot_mcp/__init__.py
robot_mcp/models.py
robot_mcp/robot_sql.py
robot_mcp/server.py
robot_mcp-0.1.0.dist-info/METADATA
robot_mcp-0.1.0.dist-info/WHEEL
robot_mcp-0.1.0.dist-info/entry_points.txt
robot_mcp-0.1.0.dist-info/RECORD
