Metadata-Version: 2.4
Name: robot-mcp
Version: 0.1.0
Summary: A MCP server for ROBOT ontology operations
Author: ROBOT Server Team
Requires-Python: <=3.13,>=3.10
Requires-Dist: click>=8.0.0
Requires-Dist: duckdb>=1.3.0
Requires-Dist: mcp>=0.1.0
Requires-Dist: pydantic>=2.11.5
Requires-Dist: pyyaml>=6.0.2
